LICENSE
MANIFEST.in
README.rst
setup.py
fann2/__init__.py
fann2/fann2.i
fann2/fann_cpp_subclass.h
fann2.egg-info/PKG-INFO
fann2.egg-info/SOURCES.txt
fann2.egg-info/dependency_links.txt
fann2.egg-info/not-zip-safe
fann2.egg-info/top_level.txt
include/compat_time.h
include/config.h
include/doublefann.h
include/fann.h
include/fann_activation.h
include/fann_cascade.h
include/fann_cpp.h
include/fann_data.h
include/fann_error.h
include/fann_internal.h
include/fann_io.h
include/fann_train.h
include/fixedfann.h
include/floatfann.h