Metadata-Version: 1.1
Name: fann2
Version: 1.0.7
Summary: Fast Artificial Neural Network Library (fann) bindings.
Home-page: https://github.com/FutureLinkCorporation/fann2
Author: Gil Megidish, Vincenzo Di Massa and FutureLinkCorporation
Author-email: gil@megidish.net & hawk.it@tiscali,it and devel@futurelinkcorporation.com
License: GNU LESSER GENERAL PUBLIC LICENSE (LGPL)
Keywords: ANN,artificial,intelligence,FANN2.2.0,bindings
Platform: UNKNOWN
Classifier: Development Status :: 4 - Beta
Classifier: Topic :: Scientific/Engineering :: Artificial Intelligence
Classifier: License :: OSI Approved :: GNU Lesser General Public License v2 or later (LGPLv2+)
Classifier: Programming Language :: Python :: 2.7
Classifier: Programming Language :: Python :: 3.3
Classifier: Programming Language :: Python :: 3.4
